{
	"asset": {
		"version": "1.0"
	},
	"geometricError": 1.0825317547305482,
	"root": {
		"children": [
			{
				"content": {
					"uri": "2/content.pnts"
				},
				"boundingVolume": {
					"region": [
						0.07609308047371456,
						0.7650611225923684,
						0.07609520708015906,
						0.7650620402324911,
						104.0925,
						105.31875
					]
				},
				"geometricError": 0.5412658773652741,
				"refine": "ADD"
			},
			{
				"content": {
					"uri": "4/content.pnts"
				},
				"boundingVolume": {
					"region": [
						0.07609308047371456,
						0.7650602049514311,
						0.07609520708015906,
						0.7650611225923684,
						105.31875,
						106.54499999999999
					]
				},
				"geometricError": 0.5412658773652741,
				"refine": "ADD"
			},
			{
				"content": {
					"uri": "6/content.pnts"
				},
				"boundingVolume": {
					"region": [
						0.07609308047371456,
						0.7650611225923684,
						0.07609520708015906,
						0.7650620402324911,
						105.31875,
						106.54499999999999
					]
				},
				"geometricError": 0.5412658773652741,
				"refine": "ADD"
			}
		],
		"content": {
			"uri": "content.pnts"
		},
		"boundingVolume": {
			"region": [
				0.07609308047371456,
				0.7650602049514311,
				0.07609733368660355,
				0.7650620402324911,
				104.0925,
				106.54499999999999
			]
		},
		"geometricError": 1.0825317547305482,
		"refine": "ADD"
	}
}